lambda_local/__init__.py
lambda_local/__main__.py
lambda_local/context.py
lambda_local/environment_variables.py
lambda_local/event.py
lambda_local/main.py
lambda_local/timeout.py
python_lambda_local-0.1.13.dist-info/LICENSE
python_lambda_local-0.1.13.dist-info/METADATA
python_lambda_local-0.1.13.dist-info/WHEEL
python_lambda_local-0.1.13.dist-info/entry_points.txt
python_lambda_local-0.1.13.dist-info/top_level.txt
python_lambda_local-0.1.13.dist-info/RECORD
