Metadata-Version: 2.1
Name: python-lambda-local
Version: 0.1.13
Summary: Run lambda function in python on local machine.
Home-page: https://github.com/HDE/python-lambda-local
Author: YANG Xudong, Iskandar Setiadi
Author-email: iskandar.setiadi@hennge.com
License: MIT
Keywords: AWS Lambda
Platform: UNKNOWN
Classifier: Development Status :: 3 - Alpha
Classifier: Operating System :: POSIX
Classifier: Programming Language :: Python
Classifier: Programming Language :: Python :: 3.7
Classifier: Programming Language :: Python :: 3.8
Classifier: Programming Language :: Python :: 3.9
Classifier: License :: OSI Approved :: MIT License
License-File: LICENSE
Requires-Dist: boto3
